<?xml version="1.0" encoding="UTF-8"?>
<ecore:EPackage xmi:version="2.0" xmlns:xmi="http://www.omg.org/XMI" xmlns:xsi="http://www.w3.org/2001/XMLSchema-instance"
    xmlns:ecore="http://www.eclipse.org/emf/2002/Ecore" name="bank" nsURI="http://www.example.org/bank" nsPrefix="bank">
  <eClassifiers xsi:type="ecore:EClass" name="Course">
    <eStructuralFeatures xsi:type="ecore:EAttribute" name="id" eType="ecore:EDataType http://www.eclipse.org/emf/2002/Ecore#//EInt"/>
    <eStructuralFeatures xsi:type="ecore:EAttribute" name="description" eType="ecore:EDataType http://www.eclipse.org/emf/2002/Ecore#//EChar"/>
    <eStructuralFeatures xsi:type="ecore:EAttribute" name="length" eType="ecore:EDataType http://www.eclipse.org/emf/2002/Ecore#//EChar"/>
    <eStructuralFeatures xsi:type="ecore:EAttribute" name="created_at" eType="ecore:EDataType http://www.eclipse.org/emf/2002/Ecore#//EDatetime"/>    
  </eClassifiers>
  <eClassifiers xsi:type="ecore:EClass" name="Account">
    <eStructuralFeatures xsi:type="ecore:EAttribute" name="accountNumber" eType="ecore:EDataType http://www.eclipse.org/emf/2002/Ecore#//EInt"/>
    <eStructuralFeatures xsi:type="ecore:EAttribute" name="balance" eType="ecore:EDataType http://www.eclipse.org/emf/2002/Ecore#//EInt"/>
  </eClassifiers>
  <eClassifiers xsi:type="ecore:EClass" name="Client">
    <eStructuralFeatures xsi:type="ecore:EAttribute" name="name" eType="ecore:EDataType http://www.eclipse.org/emf/2002/Ecore#//EString"/>
    <eStructuralFeatures xsi:type="ecore:EAttribute" name="address" eType="ecore:EDataType http://www.eclipse.org/emf/2002/Ecore#//EString"/>
    <eStructuralFeatures xsi:type="ecore:EAttribute" name="dateOfBirth" eType="ecore:EDataType http://www.eclipse.org/emf/2002/Ecore#//EInt"/>
    <eStructuralFeatures xsi:type="ecore:EAttribute" name="cardNumber" eType="ecore:EDataType http://www.eclipse.org/emf/2002/Ecore#//EInt"/>
    <eStructuralFeatures xsi:type="ecore:EAttribute" name="pin" eType="ecore:EDataType http://www.eclipse.org/emf/2002/Ecore#//EInt"/>
    <eStructuralFeatures xsi:type="ecore:EReference" name="account" lowerBound="1"
        upperBound="-1" eType="#//Account" containment="true"/>
  </eClassifiers>
  <eClassifiers xsi:type="ecore:EClass" name="atm">
    <eStructuralFeatures xsi:type="ecore:EAttribute" name="location" eType="ecore:EDataType http://www.eclipse.org/emf/2002/Ecore#//EString"/>
    <eStructuralFeatures xsi:type="ecore:EAttribute" name="availableCash" eType="ecore:EDataType http://www.eclipse.org/emf/2002/Ecore#//EInt"/>
  </eClassifiers>
</ecore:EPackage>